{"cord_uid": "h145cxlp", "sourcedb": "PMC", "sourceid": "PMC4683816", "divid": "18", "text": "One or more specific influenza - associated diagnoses / complications were reported for 42 ( 89 . 4 % ) of the 47 children ( Table 4 ) . The most frequent diagnosis was influenzaassociated pneumonia ( 61 . 7 % ) , followed by bronchitis / bronchiolitis ( 31 . 9 % ) , and secondary bacterial pneumonia ( 25 . 5 % ) . ARDS was reported for 10 ( 21 . 3 % ) and sepsis for six children ( 12 . 8 % ) ; other complications were rare . Thirty - nine of the 47 patients ( 83 . 0 % ) underwent a chest radiograph .", "project": "cdlai_CORD-19", "denotations": [{"id": "A-biobert_T1", "span": {"begin": 169, "end": 199}, "obj": "Disease"}, {"id": "A-biobert_T2", "span": {"begin": 226, "end": 237}, "obj": "Disease"}, {"id": "A-biobert_T3", "span": {"begin": 239, "end": 253}, "obj": "Disease"}, {"id": "A-biobert_T4", "span": {"begin": 282, "end": 302}, "obj": "Disease"}, {"id": "A-biobert_T5", "span": {"begin": 317, "end": 322}, "obj": "Disease"}, {"id": "A-biobert_T6", "span": {"begin": 359, "end": 366}, "obj": "Disease"}]}