{"cord_uid": "opjd4ylh", "sourcedb": "PMC", "sourceid": "PMC6949926", "divid": "26", "text": "A good working environment can facilitate better service and reduce workload . A disorganized working environment impairs the health center teams . Infrastructure includes attention to space , ventilation , comfort , and rational layout that facilitates links within the healthcare settings . The workplace has an impact on preventing TB transmission ; it serves as the first line of defense for preventing the spread of TB in the healthcare settings . Participants expressed similar sentiments about poor infrastructure .", "project": "cdlai_CORD-19", "denotations": []}