{"cord_uid": "04q71md3", "sourcedb": "PMC", "sourceid": "PMC3930559", "divid": "13", "text": "reconstructing the ancestral locations in the evolutionary history . In Text S1 , we ( i ) provide more mathematical detail of the GLM model , ( ii ) describe novel transition kernels for efficient statistical inference , ( iii ) propose prior specifications and ( iv ) explain how Bayes factors can be calculated for each predictor based on d estimates . The method introduced here is implemented in the BEAST software package [ 24 ] .", "project": "cdlai_CORD-19", "denotations": []}