{"cord_uid": "0oq4kkn5", "sourcedb": "PMC", "sourceid": "PMC5052702", "divid": "21", "text": "Maleamic acid ( 1 . 61 g , 14 mmol , 1 eq ) was djssolved in EtOH . Concentrated sulfuric acid ( 0 . 15 ml , 0 . 2 eq ) was added and the mixture was refluxed for 2 . 5 h . After removal of the solvent the white precipitate was purified over silica by MPLC with ethyl acetate / n - hexane 12 , 165 . 82 , 132 . 86 , 127 . 53 , 60 . 08 , 13 . 88 ; mp : 94 ( 2 ) , 131 . 8 ( 2 ) , 33 . 6 ( 2 ) , 14 . 4 ( 2 ) .", "project": "cdlai_CORD-19", "denotations": []}