{"cord_uid": "rn84e3ur", "sourcedb": "PMC", "sourceid": "PMC4133625", "divid": "6", "text": "According to the transmission mechanism of respiratory infectious disease , the diffusion and dispersion of the aerosols expelled by respiratory activities are important and necessary for infection risk assessment [ 18 ] . The airborne transmission of these aerosols in an airplane The removal of contaminants was not obviously affected by the moving speed Choi and Edwards [ 15 ] CFD a realistic walking human model a Room - Room and a Room - Hall configuration particle The rate of mass transport increases as the walking speed increases , but the total amount of material transported is more influenced by the initial proximity of the human from the doorway .", "project": "cdlai_CORD-19", "denotations": []}